volcanic_checker/__init__.py
volcanic_checker/checker.py
volcanic_checker/volcanolist.json
volcanic_checker/__pycache__/__init__.cpython-313.pyc
volcanic_checker/__pycache__/checker.cpython-313.pyc
volcanic_checker-0.1.2.dist-info/licenses/LICENSE
volcanic_checker-0.1.2.dist-info/METADATA
volcanic_checker-0.1.2.dist-info/WHEEL
volcanic_checker-0.1.2.dist-info/entry_points.txt
volcanic_checker-0.1.2.dist-info/top_level.txt
volcanic_checker-0.1.2.dist-info/RECORD
