Metadata-Version: 2.4
Name: volcanic_checker
Version: 0.1.2
Summary: Fetch and handle volcanic activity alerts from JMA
Home-page: https://github.com/mellllonsoda/volcanic_checker
Author: mellllonsoda
Author-email: ymellllonsoda0419@gmail.com
License: MIT
Classifier: Programming Language :: Python :: 3
Classifier: License :: OSI Approved :: MIT License
Classifier: Operating System :: OS Independent
Requires-Python: >=3.10
License-File: LICENSE
Requires-Dist: requests>=2.0
Requires-Dist: beautifulsoup4>=4.0
Dynamic: author
Dynamic: author-email
Dynamic: classifier
Dynamic: description
Dynamic: description-content-type
Dynamic: home-page
Dynamic: license
Dynamic: license-file
Dynamic: requires-dist
Dynamic: requires-python
Dynamic: summary
